{
  "$schema": "./changelog.schema.json",
  "data": [
    {
      "version": "0.8.0",
      "changes": [
        {
          "type": "misc",
          "desc": "cleanup"
        },
        {
          "type": "fix",
          "desc": "allow ping to drop"
        },
        {
          "type": "fix",
          "desc": "hecatomb score parsing"
        },
        {
          "type": "fix",
          "desc": "hypixel changed skull ids"
        },
        {
          "type": "misc",
          "desc": "custom worldLoad/Unload registers"
        },
        {
          "type": "misc",
          "desc": "log errors to console"
        },
        {
          "type": "change",
          "desc": "change text gui font rendering"
        },
        {
          "type": "misc",
          "desc": "use text shadow by default"
        },
        {
          "type": "feat",
          "desc": "add alignment to text guis"
        },
        {
          "type": "feat",
          "desc": "add font selector to text guis"
        },
        {
          "type": "feat",
          "desc": "custom font quality for text guis"
        },
        {
          "type": "fix",
          "desc": "updater message"
        },
        {
          "type": "feat",
          "desc": "changelog viewer"
        }
      ]
    },
    {
      "version": "0.8.1",
      "changes": [
        {
          "type": "fix",
          "desc": "bold text wasn't bold"
        },
        {
          "type": "fix",
          "desc": "text guis sometimes infinitely hung, whoops"
        }
      ]
    },
    {
      "version": "0.8.2",
      "changes": [
        {
          "type": "fix",
          "desc": "text gui things"
        },
        {
          "type": "change",
          "desc": "gui performance"
        },
        {
          "type": "change",
          "desc": "base font settings"
        },
        {
          "type": "misc",
          "desc": "dev tools"
        },
        {
          "type": "fix",
          "desc": "alerts flashing previous text"
        },
        {
          "type": "feat",
          "desc": "add mojangles as a font"
        }
      ]
    },
    {
      "version": "0.8.3",
      "changes": [
        {
          "type": "fix",
          "desc": "boxteammates performance"
        },
        {
          "type": "fix",
          "desc": "concurrent mod in camp"
        },
        {
          "type": "fix",
          "desc": "i may have goofed up the updater"
        }
      ]
    },
    {
      "version": "0.8.4",
      "changes": [
        {
          "type": "fix",
          "desc": "rabbit sniffer"
        },
        {
          "type": "change",
          "desc": "move cpu intensive things to .jar"
        },
        {
          "type": "change",
          "desc": "ping discrepencies in timers"
        },
        {
          "type": "change",
          "desc": "default font size"
        },
        {
          "type": "feat",
          "desc": "ice spray alert -> rare mob drop alert (now does sm cp)"
        },
        {
          "type": "misc",
          "desc": "dev tax"
        },
        {
          "type": "feat",
          "desc": "log damage numbers"
        }
      ]
    },
    {
      "version": "0.8.5",
      "changes": [
        {
          "type": "fix",
          "desc": "this updater is actually giving me a fucking headache, if you your text hud elements stopped working it's likely because the previous .jar update failed and you may have to manually replace that. if you are updating to 0.8.3 or below directly to this version then after the thing crashes you, make sure there is only 1 .jar at .minecraft/config/ChatTriggers/modules/chicktils/chicktilshelper/build/libs if there is more than one delete the older one, if it fails due to being open in openjdk or something similar, open task manager and close minecraft/the launcher/any stray javaw instances and try again. apologies for the trouble this update should fix this issue in the future. TLDR; surely you have above a middle school reading level and can read a paragraph"
        }
      ]
    },
    {
      "version": "0.8.6",
      "changes": [
        {
          "type": "fix",
          "desc": "more log damage types"
        }
      ]
    },
    {
      "version": "0.8.7",
      "changes": [
        {
          "type": "feat",
          "desc": "ashfang health display (for cheese)"
        },
        {
          "type": "fix",
          "desc": "not validating settings inputs"
        },
        {
          "type": "misc",
          "desc": "small text hud performance"
        }
      ]
    },
    {
      "version": "0.8.8",
      "changes": [
        {
          "type": "feat",
          "desc": "fero estimator"
        },
        {
          "type": "feat",
          "desc": "# arrow hits on dragon (m7)"
        },
        {
          "type": "fix",
          "desc": "arrow align block clicks"
        }
      ]
    },
    {
      "version": "0.8.9",
      "changes": [
        {
          "type": "change",
          "desc": "make text settings more useable"
        }
      ]
    },
    {
      "version": "0.8.10",
      "changes": [
        {
          "type": "fix",
          "desc": "misc in diana/rattils/essentialschat/draw"
        },
        {
          "type": "feat",
          "desc": "boxall name/class/[black/white]list"
        },
        {
          "type": "feat",
          "desc": "custom crosshair"
        },
        {
          "type": "feat",
          "desc": "custom block highlight"
        }
      ]
    },
    {
      "version": "0.8.11",
      "changes": [
        {
          "type": "change",
          "desc": "enable aa for crosshair/block highlight"
        }
      ]
    },
    {
      "version": "0.8.12",
      "changes": [
        {
          "type": "feat",
          "desc": "etherwarp helper"
        }
      ]
    },
    {
      "version": "0.8.13",
      "changes": [
        {
          "type": "misc",
          "desc": "dev tax"
        },
        {
          "type": "fix",
          "desc": "powder chest"
        },
        {
          "type": "feat",
          "desc": "add block powder chest messages"
        },
        {
          "type": "feat",
          "desc": "dungeon block overlay size"
        },
        {
          "type": "feat",
          "desc": "hide healer fairy"
        }
      ]
    },
    {
      "version": "0.8.14",
      "changes": [
        {
          "type": "feat",
          "desc": "hide divan coating particles"
        },
        {
          "type": "feat",
          "desc": "add packets (sent) per second display"
        },
        {
          "type": "misc",
          "desc": "text gui performance thing"
        }
      ]
    },
    {
      "version": "0.8.15",
      "changes": [
        {
          "type": "fix",
          "desc": "kuudra max hp is now 240m"
        },
        {
          "type": "misc",
          "desc": "dev tax"
        },
        {
          "type": "feat",
          "desc": "update sba enchant list"
        },
        {
          "type": "feat",
          "desc": "highlight smallest dhub server"
        },
        {
          "type": "change",
          "desc": "remove font size option, now dynamic"
        }
      ]
    },
    {
      "version": "0.8.16",
      "changes": [
        {
          "type": "change",
          "desc": "dev tax"
        },
        {
          "type": "fix",
          "desc": "some flare detection in low ceilings"
        },
        {
          "type": "feat",
          "desc": "terracotta respawn timer"
        },
        {
          "type": "fix",
          "desc": "dungeons not loading (no one told me :sob:)"
        },
        {
          "type": "change",
          "desc": "blend functions (rendering will look different)"
        }
      ]
    },
    {
      "version": "0.8.17",
      "changes": [
        {
          "type": "fix",
          "desc": "gfs not recognizing \"2k\" etc as an amount"
        },
        {
          "type": "fix",
          "desc": "rare race condition :("
        },
        {
          "type": "fix",
          "desc": "rhino has bad parsing"
        }
      ]
    },
    {
      "version": "0.9.0",
      "changes": [
        {
          "type": "fix",
          "desc": "null heads in dhub selector when already in smallest"
        },
        {
          "type": "fix",
          "desc": "random conc mod in avarice"
        },
        {
          "type": "fix",
          "desc": "add more cakes"
        },
        {
          "type": "fix",
          "desc": "add small brain"
        },
        {
          "type": "fix",
          "desc": "egg sniffer (but not really)"
        },
        {
          "type": "change",
          "desc": "better fero estimate"
        },
        {
          "type": "fix",
          "desc": "more /warp aliases"
        },
        {
          "type": "change",
          "desc": "arrow stack for dragons now counts time until 5 hits for t/h/m"
        },
        {
          "type": "change",
          "desc": "better camp skip timer (actually a yap skip timer now)"
        },
        {
          "type": "misc",
          "desc": "dev tax"
        },
        {
          "type": "fix",
          "desc": "add tidal enchant"
        },
        {
          "type": "fix",
          "desc": "random race cond in textgui"
        },
        {
          "type": "feat",
          "desc": "new diana solver"
        }
      ]
    },
    {
      "version": "0.9.1",
      "changes": [
        {
          "type": "feat",
          "desc": "average guess for diana"
        }
      ]
    },
    {
      "version": "0.9.2",
      "changes": [
        {
          "type": "change",
          "desc": "diana remove skytils dependency"
        },
        {
          "type": "change",
          "desc": "random diana changes"
        },
        {
          "type": "feat",
          "desc": "add revert button when settings changed"
        }
      ]
    },
    {
      "version": "0.10.0",
      "changes": [
        {
          "type": "misc",
          "desc": "dev tax"
        },
        {
          "type": "change",
          "desc": "diana stuff"
        },
        {
          "type": "fix",
          "desc": "goldor frenzy timer was off by 1"
        },
        {
          "type": "fix",
          "desc": "not boxing ice sprayed mobs when swapping off spray quickly"
        },
        {
          "type": "change",
          "desc": "not boxing the same ice sprayed mob multiple times"
        },
        {
          "type": "change",
          "desc": "box mobs scans off entity id"
        },
        {
          "type": "feat",
          "desc": "pearl path predictor"
        },
        {
          "type": "fix",
          "desc": "etherwarp display on flower pots"
        },
        {
          "type": "feat",
          "desc": "boxallentities add entity id"
        },
        {
          "type": "fix",
          "desc": "no alert sound on first game load"
        },
        {
          "type": "change",
          "desc": "m7 lb waypoints"
        },
        {
          "type": "change",
          "desc": "play key sound remove dulkir dependency"
        },
        {
          "type": "change",
          "desc": "instamid timer now uses server ticks"
        },
        {
          "type": "feat",
          "desc": "add option to highlight targetted entity"
        },
        {
          "type": "change",
          "desc": "button size for ss solver"
        },
        {
          "type": "fix",
          "desc": "lb stack in dragons sometimes having incorrect time"
        },
        {
          "type": "feat",
          "desc": "add healing pot and architect to dulkir secret sounds"
        },
        {
          "type": "fix",
          "desc": "update gfs item list"
        },
        {
          "type": "del",
          "desc": "extra settings from diana"
        }
      ]
    },
    {
      "version": "0.10.1",
      "changes": [
        {
          "type": "feat",
          "desc": "add bayou to warp list"
        },
        {
          "type": "feat",
          "desc": "add new enchants to sba"
        },
        {
          "type": "misc",
          "desc": "dev tax :("
        },
        {
          "type": "feat",
          "desc": "add hotspot scanner (off particles, not radar)"
        },
        {
          "type": "fix",
          "desc": "center lines in textgui when centered on anchor"
        },
        {
          "type": "fix",
          "desc": "mem leak when /ct reload"
        },
        {
          "type": "change",
          "desc": "/fe (floor entrance) -> /fent (to fix the mem leak trust)"
        },
        {
          "type": "feat",
          "desc": "update sba sc list"
        },
        {
          "type": "feat",
          "desc": "add bayou to stat gui"
        }
      ]
    },
    {
      "version": "0.11.0",
      "changes": [
        {
          "type": "misc",
          "desc": "update sack list"
        },
        {
          "type": "misc",
          "desc": "obligatory dev tax"
        },
        {
          "type": "feat",
          "desc": "sack item hud"
        },
        {
          "type": "change",
          "desc": "implementation of powder chest thing"
        },
        {
          "type": "misc",
          "desc": "add option to show powder from chests"
        },
        {
          "type": "fix",
          "desc": "spotify string width on different fonts"
        },
        {
          "type": "fix",
          "desc": "text sometimes appearing discolored"
        },
        {
          "type": "feat",
          "desc": "necromancy soul display (dropped souls)"
        },
        {
          "type": "change",
          "desc": "swap to apelles for rendering"
        },
        {
          "type": "del",
          "desc": "remove rabbit sniffer"
        },
        {
          "type": "fix",
          "desc": "random npe's"
        },
        {
          "type": "change",
          "desc": "box ice spray logic"
        },
        {
          "type": "change",
          "desc": "diana stuff"
        },
        {
          "type": "misc",
          "desc": "pbos for faster text rendering"
        },
        {
          "type": "misc",
          "desc": "add option to change channel for rattils message"
        },
        {
          "type": "feat",
          "desc": "dojo (only mastery rn i was skill issuing stfu)"
        },
        {
          "type": "feat",
          "desc": "timer for earliest terracotta respawn on hud"
        },
        {
          "type": "change",
          "desc": "make ender bow work with pearl path"
        },
        {
          "type": "feat",
          "desc": "add /lookat (to help aiming angles)"
        },
        {
          "type": "feat",
          "desc": "dark monolith scanner"
        },
        {
          "type": "feat",
          "desc": "dark monolith drop tracker"
        },
        {
          "type": "change",
          "desc": "start player transfer cooldown on warp message"
        },
        {
          "type": "change",
          "desc": "/cpv now uses a different api"
        },
        {
          "type": "misc",
          "desc": "a lot of dev tax :sobs:"
        }
      ]
    },
    {
      "version": "0.11.1",
      "changes": [
        {
          "type": "fix",
          "desc": "diana"
        }
      ]
    },
    {
      "version": "0.12.0",
      "changes": [
        {
          "type": "fix",
          "desc": "hidehealerpowerups"
        },
        {
          "type": "change",
          "desc": "diana stuff i forgot"
        },
        {
          "type": "feat",
          "desc": "storm term laser warning"
        },
        {
          "type": "fix",
          "desc": "server ticks now start sending instantly"
        },
        {
          "type": "misc",
          "desc": "reopen settings gui after editing text position"
        },
        {
          "type": "feat",
          "desc": "toggling settings will now hide dependents"
        },
        {
          "type": "fix",
          "desc": "spacing issue with chatting (issue on their end) :("
        },
        {
          "type": "fix",
          "desc": "pearlpath on snow layers"
        },
        {
          "type": "fix",
          "desc": "dungeon now reactivates when reconnecting"
        },
        {
          "type": "feat",
          "desc": "entityreducer to cull useless entities"
        },
        {
          "type": "fix",
          "desc": "parsing names in sacktils"
        },
        {
          "type": "misc",
          "desc": "update sack list"
        },
        {
          "type": "fix",
          "desc": "chattils waypoint not capitalizing name in chat message"
        },
        {
          "type": "misc",
          "desc": "more melody messages!"
        },
        {
          "type": "feat",
          "desc": "hide soulweaver gloves skulls"
        },
        {
          "type": "misc",
          "desc": "update sba enchant list"
        },
        {
          "type": "misc",
          "desc": "move kuudra skypearl timer"
        },
        {
          "type": "misc",
          "desc": "change backend rendering"
        },
        {
          "type": "feat",
          "desc": "kuudra simplify pickup title"
        },
        {
          "type": "misc",
          "desc": "settings/data will create backup if fail to parse"
        },
        {
          "type": "misc",
          "desc": "improve text rendering performance"
        },
        {
          "type": "change",
          "desc": "remove party leader req from echat forwarding"
        },
        {
          "type": "feat",
          "desc": "delete undeleted entities from voidgloom laser"
        },
        {
          "type": "fix",
          "desc": "duplicate buttons in simon says when prematurely clicking sea lanterns"
        },
        {
          "type": "fix",
          "desc": "z-fighting in pearlpath"
        },
        {
          "type": "misc",
          "desc": "update warp list"
        },
        {
          "type": "feat",
          "desc": "skypearl for build -> p4 dps"
        },
        {
          "type": "misc",
          "desc": "do not box ghost mobs (dungeons)"
        },
        {
          "type": "feat",
          "desc": "guess state of prince/mimic/paul from scoreboard"
        },
        {
          "type": "change",
          "desc": "expand trigger boxes of simon says/arrow align"
        },
        {
          "type": "change",
          "desc": "goldor frenzy timer shows time until first tick"
        },
        {
          "type": "misc",
          "desc": "update etherwarp calculator and move to jar"
        },
        {
          "type": "fix",
          "desc": "own flux detection"
        },
        {
          "type": "change",
          "desc": "remove fps limiter from serverscrutinizers"
        },
        {
          "type": "feat",
          "desc": "more options in spotify display"
        },
        {
          "type": "feat",
          "desc": "lag-proof wither shield timer"
        },
        {
          "type": "fix",
          "desc": "dont complain about no packets in singleplayer (lastpacket)"
        }
      ]
    }
  ]
}